argparse_action/__init__.py
argparse_action/action.py
argparse_action/logging.py
argparse_action-0.5.2.dist-info/LICENSE
argparse_action-0.5.2.dist-info/METADATA
argparse_action-0.5.2.dist-info/WHEEL
argparse_action-0.5.2.dist-info/top_level.txt
argparse_action-0.5.2.dist-info/RECORD
