Metadata-Version: 2.1
Name: argparse_action
Version: 0.5.2
Summary: configure argparse from function signature
Home-page: https://github.com/nyirog/argparse_action
Maintainer: Nyiro Gergo
Maintainer-email: gergo@nyiro.name
License: Apache 2
Project-URL: Documentation, https://argparse-action.readthedocs.io/en/latest/
Project-URL: Source, https://github.com/nyirog/argparse_action
Project-URL: Tracker, https://github.com/nyirog/argparse_action/issues
Platform: UNKNOWN
Classifier: Programming Language :: Python :: 3
Classifier: License :: OSI Approved :: Apache Software License
Classifier: Operating System :: OS Independent
Classifier: Environment :: Console
Requires-Python: >=3.6
License-File: LICENSE
